aws_access_advisor/__init__.py
aws_access_advisor/__main__.py
aws_access_advisor-2024.1.0.0.dist-info/METADATA
aws_access_advisor-2024.1.0.0.dist-info/WHEEL
aws_access_advisor-2024.1.0.0.dist-info/RECORD
